vixen/__init__.py
vixen/cli.py
vixen/common.py
vixen/directory.py
vixen/media.py
vixen/processor.py
vixen/project.py
vixen/ui_utils.py
vixen/vixen.py
vixen/vixen_ui.py
vixen/html/vixen_ui.html
vixen/html/css/style.css
vixen/html/images/loading.gif
vixen/html/images/logo.png
vixen/html/images/logo_small.png
vixen/html/js/mousetrap.min.js
vixen/html/js/notify.min.js
vixen/integration_tests/__init__.py
vixen/integration_tests/test_ui.py
vixen/tests/__init__.py
vixen/tests/test_cli.py
vixen/tests/test_common.py
vixen/tests/test_directory.py
vixen/tests/test_media.py
vixen/tests/test_pager.py
vixen/tests/test_processor.py
vixen/tests/test_project.py
vixen/tests/test_vixen.py
vixen-1.0rc3.dist-info/METADATA
vixen-1.0rc3.dist-info/RECORD
vixen-1.0rc3.dist-info/WHEEL
vixen-1.0rc3.dist-info/entry_points.txt
vixen-1.0rc3.dist-info/top_level.txt
