Metadata-Version: 2.1
Name: vixen
Version: 1.0rc3
Summary: View eXtract and aNnotate media
Home-page: https://github.com/vixen-project/vixen
Author: Prabhu Ramachandran and Kadambari Devarajan
Author-email: vixen@googlegroups.com
License: UNKNOWN
Platform: UNKNOWN
Classifier: Development Status :: 5 - Production/Stable
Classifier: Environment :: Web Environment
Classifier: Intended Audience :: Developers
Classifier: Intended Audience :: Education
Classifier: Intended Audience :: End Users/Desktop
Classifier: Intended Audience :: Science/Research
Classifier: License :: OSI Approved :: BSD License
Classifier: Natural Language :: English
Classifier: Operating System :: OS Independent
Classifier: Programming Language :: Python
Classifier: Programming Language :: Python :: 2.7
Classifier: Programming Language :: Python :: 3.4
Classifier: Programming Language :: Python :: 3.5
Classifier: Programming Language :: Python :: 3.6
Classifier: Topic :: Scientific/Engineering :: Information Analysis
Classifier: Topic :: Utilities
Requires-Python: <3.7
Requires-Dist: traits
Requires-Dist: jigna
Requires-Dist: tornado (<5.0)
Requires-Dist: json-tricks (>=3.0)
Requires-Dist: whoosh
Requires-Dist: backports.csv
